bus_16/__init__.py
bus_16/bus.py
bus_16/__pycache__/__init__.cpython-310.pyc
bus_16/__pycache__/bus.cpython-310.pyc
bus_16/log/bus.log
bus_16/utils/__init__.py
bus_16/utils/setup_logger.py
bus_16/utils/__pycache__/__init__.cpython-310.pyc
bus_16/utils/__pycache__/setup_logger.cpython-310.pyc
bus_16_manjevas-0.0.1.dist-info/LICENSE
bus_16_manjevas-0.0.1.dist-info/METADATA
bus_16_manjevas-0.0.1.dist-info/WHEEL
bus_16_manjevas-0.0.1.dist-info/top_level.txt
bus_16_manjevas-0.0.1.dist-info/RECORD
