Metadata-Version: 2.1
Name: bus-16-manjevas
Version: 0.0.1
Summary: A 16-bit memory address, 8-bit data bus emulator.
Home-page: https://github.com/mcsrinivasa/bus-16.git
Author: Manjunath Srinivasa
Author-email: Manju Srinivasa <manjevas@outlook.com>
Project-URL: Homepage, https://github.com/mcsrinivasa/bus-16
Project-URL: Issues, https://github.com/mcsrinivasa/bus-16/issues
Classifier: Programming Language :: Python :: 3
Classifier: License :: OSI Approved :: MIT License
Classifier: Operating System :: OS Independent
Requires-Python: >=3.6
License-File: LICENSE
